src/__init__.py
src/__main__.py
src/luagram/__init__.py
src/luagram/enums.py
src/luagram/luagram.py
src/luagram/response.py
src/luagram/gadget/__init__.py
src/luagram/gadget/tdjson.py
src/luagram/gadget/tools.py
luagram-1.0.2.dist-info/METADATA
luagram-1.0.2.dist-info/WHEEL
luagram-1.0.2.dist-info/entry_points.txt
luagram-1.0.2.dist-info/top_level.txt
luagram-1.0.2.dist-info/RECORD
